devtools/__init__.py
devtools/data/black.toml
devtools/data/isort.toml
devtools/data/python-semantic-release.toml
bfiola_devtools-1.1.1.dist-info/METADATA
bfiola_devtools-1.1.1.dist-info/WHEEL
bfiola_devtools-1.1.1.dist-info/entry_points.txt
bfiola_devtools-1.1.1.dist-info/top_level.txt
bfiola_devtools-1.1.1.dist-info/RECORD
