Metadata-Version: 2.1
Name: bfiola-devtools
Version: 1.1.1
Requires-Dist: black
Requires-Dist: build
Requires-Dist: click
Requires-Dist: isort
Requires-Dist: packaging
Requires-Dist: pydantic
Requires-Dist: python-semantic-release
Requires-Dist: toml
Requires-Dist: twine
Provides-Extra: dev
